axion/__init__.py
axion/axion.py
axion/models.py
axion/ta.py
axion/utils.py
axion/visualize.py
axionquant_sdk-1.1.0.dist-info/METADATA
axionquant_sdk-1.1.0.dist-info/WHEEL
axionquant_sdk-1.1.0.dist-info/top_level.txt
axionquant_sdk-1.1.0.dist-info/RECORD
