Metadata-Version: 2.4
Name: axionquant-sdk
Version: 1.1.0
Summary: Short description
Author-email: AxionQuant <admin@axionquant.com>
License: MIT
Project-URL: Homepage, https://github.com/axionquant/python-sdk
Requires-Python: >=3.8
Requires-Dist: requests>=2.28.0
Requires-Dist: pandas>=1.5.0
Requires-Dist: numpy>=1.21.0
Requires-Dist: ipython
Requires-Dist: plotly
Requires-Dist: tensorflow
Requires-Dist: scikit-learn
Requires-Dist: tqdm
Requires-Dist: parsedatetime
Provides-Extra: dev
